{
  "/dizi/como-agua-para-chocolate": {
    "group": "Como Agua para Chocolate",
    "last_season": 1,
    "last_episode": 0,
    "start_episode": 1,
    "year": "2024",
    "imdb": "8.2",
    "poster": "https://image.tmdb.org/t/p/w500/pXNcd4z8eBihLO9I7bIVoK4mtQt.jpg"
  },
  "/dizi/dark-winds": {
    "group": "Dark Winds",
    "last_season": 1,
    "last_episode": 0,
    "start_episode": 1,
    "year": "2022",
    "imdb": "7.6",
    "poster": "https://image.tmdb.org/t/p/w500/kDlrMN0P9ByrEH2GoRbBFeZHbcf.jpg"
  },
  "/dizi/girl-from-nowhere-the-reset": {
    "group": "Girl from Nowhere: The Reset",
    "last_season": 1,
    "last_episode": 0,
    "start_episode": 1,
    "year": "2026",
    "imdb": "6.4",
    "poster": "https://image.tmdb.org/t/p/w500/bRMEjZHvES9XLKSFVCtveFGdOHC.jpg"
  },
  "/dizi/gone": {
    "group": "Gone",
    "last_season": 1,
    "last_episode": 0,
    "start_episode": 1,
    "year": "2026",
    "imdb": "7.2",
    "poster": "https://image.tmdb.org/t/p/w500/qnxKB5HlkAZZcyIiITIV7dAUX7u.jpg"
  },
  "/dizi/still-shining": {
    "group": "Still Shining",
    "last_season": 1,
    "last_episode": 0,
    "start_episode": 1,
    "year": "2026",
    "imdb": "8.1",
    "poster": "https://image.tmdb.org/t/p/w500/tVOq3YkCTnbrycnXHmth9f6qYs7.jpg"
  },
  "/dizi/boston-blue": {
    "group": "Boston Blue",
    "last_season": 1,
    "last_episode": 0,
    "start_episode": 1,
    "year": "2025",
    "imdb": "6.9",
    "poster": "https://image.tmdb.org/t/p/w500/8pyxutHxpgBt8ZwbIG2TZWCW394.jpg"
  },
  "/dizi/fire-country": {
    "group": "Fire Country",
    "last_season": 1,
    "last_episode": 0,
    "start_episode": 1,
    "year": "2022",
    "imdb": "7.1",
    "poster": "https://image.tmdb.org/t/p/w500/6XnA02VRG4dhBpTZWGZuXQdYGDW.jpg"
  },
  "/dizi/happy-s-place": {
    "group": "Happy’s Place",
    "last_season": 1,
    "last_episode": 0,
    "start_episode": 1,
    "year": "2024",
    "imdb": "5.3",
    "poster": "https://image.tmdb.org/t/p/w500/3dehoKPCwLwKTWATfzGqoJ2Psdl.jpg"
  },
  "/dizi/law-order-toronto-criminal-intent": {
    "group": "Law & Order Toronto: Criminal Intent",
    "last_season": 1,
    "last_episode": 0,
    "start_episode": 1,
    "year": "2024",
    "imdb": "7.0",
    "poster": "https://image.tmdb.org/t/p/w500/eqD7W5EGue5Nvg0BNEnoRyMQAcz.jpg"
  },
  "/dizi/sheriff-country": {
    "group": "Sheriff Country",
    "last_season": 1,
    "last_episode": 0,
    "start_episode": 1,
    "year": "2025",
    "imdb": "7.2",
    "poster": "https://image.tmdb.org/t/p/w500/hBrbAYp4SGMkNYZGPeFhEd0xW7Z.jpg"
  },
  "/dizi/stumble": {
    "group": "Stumble",
    "last_season": 1,
    "last_episode": 0,
    "start_episode": 1,
    "year": "2025",
    "imdb": "7.2",
    "poster": "https://image.tmdb.org/t/p/w500/yb9x05LNrgs06QjAYZE7A4UvSuj.jpg"
  },
  "/dizi/the-madison": {
    "group": "The Madison",
    "last_season": 1,
    "last_episode": 0,
    "start_episode": 1,
    "year": "2026",
    "imdb": "7.0",
    "poster": "https://image.tmdb.org/t/p/w500/nZVRyqVbDqfLSOrLcsGGTUHccZ8.jpg"
  },
  "/dizi/american-classic": {
    "group": "American Classic",
    "last_season": 1,
    "last_episode": 0,
    "start_episode": 1,
    "year": "2026",
    "imdb": "7.0",
    "poster": "https://image.tmdb.org/t/p/w500/nQoTcFVB9xO6tLnoSARRViitPQF.jpg"
  },
  "/dizi/the-capture": {
    "group": "The Capture",
    "last_season": 1,
    "last_episode": 0,
    "start_episode": 1,
    "year": "2019",
    "imdb": "8.0",
    "poster": "https://image.tmdb.org/t/p/w500/bCuTIRmnd6eBNZ9oBBQ2KAtErid.jpg"
  },
  "/dizi/dtf-st-louis": {
    "group": "DTF St. Louis",
    "last_season": 1,
    "last_episode": 0,
    "start_episode": 1,
    "year": "2026",
    "imdb": "7.9",
    "poster": "https://image.tmdb.org/t/p/w500/xHfafw9UmomDc7jO25s9MpiL4Zs.jpg"
  },
  "/dizi/paradise": {
    "group": "Paradise",
    "last_season": 1,
    "last_episode": 0,
    "start_episode": 1,
    "year": "2025",
    "imdb": "7.0",
    "poster": "https://image.tmdb.org/t/p/w500/l8RqfhqEk04W5sSOjQ9zeWU1DyM.jpg"
  },
  "/dizi/rooster": {
    "group": "Rooster",
    "last_season": 1,
    "last_episode": 0,
    "start_episode": 1,
    "year": "2026",
    "imdb": "6.2",
    "poster": "https://image.tmdb.org/t/p/w500/aikvD4Nu7N6ekbrXNua8vJlO8JU.jpg"
  },
  "/dizi/tracker": {
    "group": "Tracker",
    "last_season": 1,
    "last_episode": 0,
    "start_episode": 1,
    "year": "2024",
    "imdb": "6.4",
    "poster": "https://image.tmdb.org/t/p/w500/otula4h1ITZ0eV84eg7Lb8u614C.jpg"
  },
  "/dizi/universal-basic-guys": {
    "group": "Universal Basic Guys",
    "last_season": 1,
    "last_episode": 0,
    "start_episode": 1,
    "year": "2025",
    "imdb": "4.9",
    "poster": "https://image.tmdb.org/t/p/w500/hdoEXYV82N3wMmWdvFinjyNOCt2.jpg"
  },
  "/dizi/watson": {
    "group": "Watson",
    "last_season": 1,
    "last_episode": 0,
    "start_episode": 1,
    "year": "2025",
    "imdb": "5.2",
    "poster": "https://image.tmdb.org/t/p/w500/b1sELCj9LK5a3olbLhPZlP8Liba.jpg"
  },
  "/dizi/marshals": {
    "group": "Marshals",
    "last_season": 1,
    "last_episode": 0,
    "start_episode": 1,
    "year": "2026",
    "imdb": "6.3",
    "poster": "https://image.tmdb.org/t/p/w500/nInfaveN1iFpRIcMGNKENoVVUT2.jpg"
  },
  "/dizi/siren-s-kiss": {
    "group": "Siren’s Kiss",
    "last_season": 1,
    "last_episode": 0,
    "start_episode": 1,
    "year": "2026",
    "imdb": "7.7",
    "poster": "https://image.tmdb.org/t/p/w500/8r8YU97YfSf6QtMKfePmTqhFTeQ.jpg"
  },
  "/dizi/dmv": {
    "group": "DMV",
    "last_season": 1,
    "last_episode": 0,
    "start_episode": 1,
    "year": "2025",
    "imdb": "5.6",
    "poster": "https://image.tmdb.org/t/p/w500/nLCpxH7BhFwP50lF0VFpxeeFjmM.jpg"
  },
  "/dizi/fbi": {
    "group": "FBI",
    "last_season": 1,
    "last_episode": 0,
    "start_episode": 1,
    "year": "2018",
    "imdb": "7.1",
    "poster": "https://image.tmdb.org/t/p/w500/zfKS4WL0OZ9udpNoSYZw91VB3aH.jpg"
  },
  "/dizi/these-sacred-vows": {
    "group": "These Sacred Vows",
    "last_season": 1,
    "last_episode": 0,
    "start_episode": 1,
    "year": "2026",
    "imdb": "7.3",
    "poster": "https://image.tmdb.org/t/p/w500/dC14qy2K8X28aKIwh1oXAhpZsGd.jpg"
  },
  "/dizi/when-calls-the-heart": {
    "group": "When Calls the Heart",
    "last_season": 1,
    "last_episode": 0,
    "start_episode": 1,
    "year": "2014",
    "imdb": "7.9",
    "poster": "https://image.tmdb.org/t/p/w500/3d8XxE3qDLzeewtaC4DGamI6Ofa.jpg"
  },
  "/dizi/dona-beja": {
    "group": "Dona Beja",
    "last_season": 1,
    "last_episode": 0,
    "start_episode": 1,
    "year": "2026",
    "imdb": "6.2",
    "poster": "https://image.tmdb.org/t/p/w500/fB8khOzVqpQWhVfIXUQgCokP9XR.jpg"
  },
  "/dizi/cia": {
    "group": "CIA",
    "last_season": 1,
    "last_episode": 0,
    "start_episode": 1,
    "year": "2026",
    "imdb": "7.3",
    "poster": "https://image.tmdb.org/t/p/w500/8XbgWv137Umc8resTDeWh9ff7Y0.jpg"
  },
  "/dizi/memory-of-a-killer": {
    "group": "Memory of a Killer",
    "last_season": 1,
    "last_episode": 0,
    "start_episode": 1,
    "year": "2026",
    "imdb": "7.6",
    "poster": "https://image.tmdb.org/t/p/w500/3kpXrWW6gmlngwgSa52IhBpjPuz.jpg"
  },
  "/dizi/st-denis-medical": {
    "group": "St. Denis Medical",
    "last_season": 1,
    "last_episode": 0,
    "start_episode": 1,
    "year": "2024",
    "imdb": "6.9",
    "poster": "https://image.tmdb.org/t/p/w500/8tUjI21ZcfSynLCk3Zr0Gs5BQwz.jpg"
  },
  "/dizi/age-of-attraction": {
    "group": "Age of Attraction",
    "last_season": 1,
    "last_episode": 0,
    "start_episode": 1,
    "year": "2026",
    "imdb": "4.7",
    "poster": "https://image.tmdb.org/t/p/w500/86zlBZhuhuE2FlXn8lGxixCQ4aS.jpg"
  },
  "/dizi/cross": {
    "group": "Cross",
    "last_season": 1,
    "last_episode": 0,
    "start_episode": 1,
    "year": "2024",
    "imdb": "7.2",
    "poster": "https://image.tmdb.org/t/p/w500/6hhKdavCEZi8d584ZtIrQIrBvZI.jpg"
  },
  "/dizi/emerg-ncia-radioativa": {
    "group": "Emergência Radioativa",
    "last_season": 1,
    "last_episode": 0,
    "start_episode": 1,
    "year": "2026",
    "imdb": "7.0",
    "poster": "https://image.tmdb.org/t/p/w500/u21TjnyVRB3hxrvvC0Ia2NHgJX8.jpg"
  },
  "/dizi/furies": {
    "group": "Furies",
    "last_season": 1,
    "last_episode": 0,
    "start_episode": 1,
    "year": "2024",
    "imdb": "6.6",
    "poster": "https://image.tmdb.org/t/p/w500/8sHKc6kNKjdhvHBP2c5zoSS16v5.jpg"
  },
  "/dizi/imperfect-women": {
    "group": "Imperfect Women",
    "last_season": 1,
    "last_episode": 0,
    "start_episode": 1,
    "year": "2026",
    "imdb": "7.0",
    "poster": "https://image.tmdb.org/t/p/w500/wW7rimhnokiQ8V6ha6VKIwHg8IV.jpg"
  },
  "/dizi/invincible": {
    "group": "Invincible",
    "last_season": 1,
    "last_episode": 0,
    "start_episode": 1,
    "year": "2021",
    "imdb": "8.7",
    "poster": "https://image.tmdb.org/t/p/w500/4tblBrslcKSifMVZ3TmtT2ukMor.jpg"
  },
  "/dizi/ncis-sydney": {
    "group": "NCIS: Sydney",
    "last_season": 1,
    "last_episode": 0,
    "start_episode": 1,
    "year": "2023",
    "imdb": "5.9",
    "poster": "https://image.tmdb.org/t/p/w500/6dYDa6h1AOZ7iZ1zv3nlw7qhErX.jpg"
  },
  "/dizi/shrinking": {
    "group": "Shrinking",
    "last_season": 1,
    "last_episode": 0,
    "start_episode": 1,
    "year": "2023",
    "imdb": "8.0",
    "poster": "https://image.tmdb.org/t/p/w500/zEFKMNPBKq6JG7uuDkzTQ9WwErn.jpg"
  },
  "/dizi/traques": {
    "group": "Traqués",
    "last_season": 1,
    "last_episode": 0,
    "start_episode": 1,
    "year": "2025",
    "imdb": "5.4",
    "poster": "https://image.tmdb.org/t/p/w500/ipf1giXcXX50ylcmDBtDcXHMTaa.jpg"
  },
  "/dizi/will-trent": {
    "group": "Will Trent",
    "last_season": 1,
    "last_episode": 0,
    "start_episode": 1,
    "year": "2023",
    "imdb": "7.7",
    "poster": "https://image.tmdb.org/t/p/w500/qG5O46gUxxYGImld03tl2zLhvrg.jpg"
  }
}